{
  "context": {
    "version": "2.0.0",
    "action": "on_confirm",
    "domain": "beckn.one:deg:ev-charging",
    "location": {
      "country": {
        "code": "IND"
      },
      "city": {
        "code": "std:080"
      }
    },
    "bap_id": "ev-charging.sandbox1.com",
    "bap_uri": "http://ev-charging-kafka-bap-onix-kafka-bap-service:8001/bap/receiver",
    "bpp_id": "ev-charging.sandbox2.com",
    "bpp_uri": "http://ev-charging-kafka-bpp-onix-kafka-bpp-service:8002/bpp/receiver",
    "transaction_id": "550e8400-e29b-41d4-a716-446655440000",
    "message_id": "440e8400-e29b-41d4-a716-446655440012",
    "timestamp": "2025-01-27T10:00:00Z",
    "ttl": "PT30S",
    "schema_context": [
      "https://raw.githubusercontent.com/beckn/protocol-specifications-new/refs/heads/main/schemas/charging_service/v1/context.jsonld"
    ]
  },
  "message": {
    "order": {
      "@context": "https://becknprotocol.io/schemas/core/v2/Order/schema-context.jsonld",
      "@type": "beckn:Order",
      "beckn:id": "order-bpp-789012",
      "beckn:orderStatus": "CONFIRMED",
      "beckn:orderNumber": "ORD-2025-001",
      "beckn:seller": "cpo1.com",
      "beckn:buyer": {
        "@context": "https://becknprotocol.io/schemas/core/v2/Party/schema-context.jsonld",
        "@type": "beckn:Party",
        "beckn:id": "user-123",
        "beckn:role": "BUYER",
        "beckn:name": "Ravi Kumar",
        "beckn:organization": {
          "descriptor": {
            "name": "GreenCharge Pvt Ltd"
          }
        },
        "beckn:address": "Apartment 123, MG Road, Bengaluru, Karnataka, 560001, India",
        "beckn:email": "ravi.kumar@greencharge.com",
        "beckn:phone": "+918765432100",
        "beckn:taxId": "GSTIN29ABCDE1234F1Z5"
      },
      "beckn:orderItems": [
        {
          "beckn:lineId": "line-001",
          "beckn:orderedItem": "pe-charging-01",
          "beckn:acceptedOffer": {
            "@context": "https://becknprotocol.io/schemas/core/v2/Offer/schema-context.jsonld",
            "@type": "beckn:Offer",
            "beckn:id": "offer-001",
            "beckn:descriptor": {
              "name": "EV Charging Session Offer",
              "short_desc": "Fast charging session with CCS2 connector"
            },
            "beckn:price": {
              "currency": "INR",
              "value": 18.0,
              "applicableQuantity": {
                "unitText": "Kilowatt Hour",
                "unitCode": "KWH",
                "unitQuantity": 1
              }
            }
          },
          "beckn:quantity": 5,
          "beckn:price": {
            "currency": "INR",
            "value": 90.0,
            "applicableQuantity": {
              "unitText": "Kilowatt Hour",
              "unitCode": "KWH",
              "unitQuantity": 5
            }
          }
        }
      ],
      "beckn:orderValue": {
        "currency": "INR",
        "value": 100.0,
        "components": [
          {
            "type": "UNIT",
            "value": 72.73,
            "currency": "INR",
            "description": "Charging session cost (4.04 kWh @ \u20b918.00/kWh)"
          },
          {
            "type": "FEE",
            "value": 10.0,
            "currency": "INR",
            "description": "Service fee"
          },
          {
            "type": "FEE",
            "value": 13.64,
            "currency": "INR",
            "description": "Overcharge estimation"
          },
          {
            "type": "SURCHARGE",
            "value": 14.55,
            "currency": "INR",
            "description": "Surge price (20%)"
          },
          {
            "type": "DISCOUNT",
            "value": -10.92,
            "currency": "INR",
            "description": "Offer discount (20%)"
          }
        ]
      },
      "beckn:fulfillment": {
        "@context": "https://becknprotocol.io/schemas/core/v2/Fulfillment/schema-context.jsonld",
        "@type": "beckn:Fulfillment",
        "beckn:id": "fulfillment-001",
        "beckn:status": "PENDING",
        "beckn:deliveryAttributes": {
          "@type": "ChargingSession",
          "sessionId": "session-001",
          "sessionType": "CHARGING",
          "startTime": "2025-01-27T10:00:00Z",
          "endTime": "2025-01-27T11:30:00Z",
          "customer": {
            "name": "Ravi Kumar",
            "phone": "+91-9887766554"
          },
          "vehicle": {
            "make": "Tata",
            "model": "Nexon EV"
          },
          "location": {
            "gps": "28.345345,77.389754",
            "address": "Connaught Place, New Delhi",
            "descriptor": {
              "name": "BlueCharge Connaught Place Station"
            }
          },
          "connectorType": "CCS2",
          "maxPowerKW": 50,
          "stationStatus": "Available",
          "authorizationMode": "OTP",
          "authorizationToken": "7484"
        }
      },
      "beckn:payment": {
        "@context": "https://becknprotocol.io/schemas/core/v2/Payment/schema-context.jsonld",
        "@type": "beckn:Payment",
        "beckn:id": "payment-123e4567-e89b-12d3-a456-426614174000",
        "beckn:status": "PAID",
        "beckn:amount": {
          "currency": "INR",
          "value": 100.0
        },
        "beckn:paymentURL": "https://payments.bluechargenet-aggregator.io/pay?transaction_id=$transaction_id&amount=$amount",
        "beckn:txnRef": "TXN-123456789",
        "beckn:paidAt": "2025-01-27T10:05:00Z",
        "beckn:method": {
          "@type": "beckn:PaymentMethod",
          "type": "schema:UPI",
          "details": {
            "vpa": "user@paytm"
          }
        },
        "beckn:acceptedPaymentMethods": [
          "schema:BankTransfer",
          "schema:UPI",
          "schema:Wallet"
        ],
        "beckn:beneficiary": "BPP"
      },
      "beckn:orderAttributes": {
        "@type": "ChargingSession",
        "sessionPreferences": {
          "preferredStartTime": "2025-01-27T10:00:00Z",
          "preferredEndTime": "2025-01-27T11:30:00Z",
          "notificationPreferences": {
            "email": true,
            "sms": true,
            "push": false
          }
        },
        "authorizationMode": "OTP",
        "authorizationOtpHint": "OTP will be shared to the user's registered number to confirm order"
      },
      "beckn:confirmedAt": "2025-01-27T10:05:00Z"
    }
  }
}